LICENSE
README.md
setup.cfg
setup.py
djina/__init__.py
djina/api.py
djina.egg-info/PKG-INFO
djina.egg-info/SOURCES.txt
djina.egg-info/dependency_links.txt
djina.egg-info/requires.txt
djina.egg-info/top_level.txt